dw_auditor/__init__.py
dw_auditor/__main__.py
dw_auditor/analysis/__init__.py
dw_auditor/analysis/relationship_detector.py
dw_auditor/checks/__init__.py
dw_auditor/checks/date_future_check.py
dw_auditor/checks/date_outlier_check.py
dw_auditor/checks/date_range_check.py
dw_auditor/checks/numeric_range_check.py
dw_auditor/checks/string_case_check.py
dw_auditor/checks/string_leading_check.py
dw_auditor/checks/string_regex_check.py
dw_auditor/checks/string_trailing_check.py
dw_auditor/checks/timestamp_pattern_check.py
dw_auditor/checks/uniqueness_check.py
dw_auditor/cli/__init__.py
dw_auditor/cli/argument_parser.py
dw_auditor/cli/config_discovery.py
dw_auditor/cli/config_template.py
dw_auditor/cli/cost_estimation.py
dw_auditor/cli/init_command.py
dw_auditor/cli/main.py
dw_auditor/cli/output.py
dw_auditor/cli/table_discovery.py
dw_auditor/core/__init__.py
dw_auditor/core/auditor.py
dw_auditor/core/base_check.py
dw_auditor/core/base_insight.py
dw_auditor/core/config.py
dw_auditor/core/exporter_mixin.py
dw_auditor/core/insight_registry.py
dw_auditor/core/insight_runner.py
dw_auditor/core/registry.py
dw_auditor/core/runner.py
dw_auditor/core/type_converter.py
dw_auditor/core/db_connection/__init__.py
dw_auditor/core/db_connection/base.py
dw_auditor/core/db_connection/bigquery.py
dw_auditor/core/db_connection/connection.py
dw_auditor/core/db_connection/databricks.py
dw_auditor/core/db_connection/metadata_helpers.py
dw_auditor/core/db_connection/snowflake.py
dw_auditor/core/db_connection/utils.py
dw_auditor/exporters/__init__.py
dw_auditor/exporters/dataframe_export.py
dw_auditor/exporters/json_export.py
dw_auditor/exporters/run_summary_export.py
dw_auditor/exporters/summary_export.py
dw_auditor/exporters/html/__init__.py
dw_auditor/exporters/html/assets.py
dw_auditor/exporters/html/checks.py
dw_auditor/exporters/html/export.py
dw_auditor/exporters/html/helpers.py
dw_auditor/exporters/html/insights.py
dw_auditor/exporters/html/relationships.py
dw_auditor-0.2.2.dist-info/licenses/LICENSE
dw_auditor-0.2.2.dist-info/METADATA
dw_auditor-0.2.2.dist-info/WHEEL
dw_auditor-0.2.2.dist-info/entry_points.txt
dw_auditor-0.2.2.dist-info/top_level.txt
dw_auditor-0.2.2.dist-info/RECORD
