Metadata-Version: 2.4
Name: dw-auditor
Version: 0.2.2
Summary: High-performance data quality auditing for BigQuery, Snowflake & Databricks
Author-email: Valentin Cathelain <valentin.cathelain.data@gmail.com>
License-Expression: MIT
Project-URL: Homepage, https://github.com/v-cth/database_audit
Project-URL: Repository, https://github.com/v-cth/database_audit
Project-URL: Issues, https://github.com/v-cth/database_audit/issues
Keywords: data-quality,data engineering,bigquery,snowflake,databricks,audit,ibis
Requires-Python: >=3.10
License-File: LICENSE
Requires-Dist: polars>=0.20.0
Requires-Dist: pyyaml>=6.0
Requires-Dist: pydantic>=2.0.0
Requires-Dist: ibis-framework[duckdb]>=9.0.0
Requires-Dist: ibis-framework[bigquery]>=9.0.0
Requires-Dist: ibis-framework[snowflake]>=9.0.0
Requires-Dist: ibis-framework[databricks]>=9.0.0
Requires-Dist: google-cloud-bigquery>=3.0.0
Requires-Dist: snowflake-connector-python>=3.0.0
Requires-Dist: platformdirs>=3.0.0
Requires-Dist: sqlglot>=20.0.0
Provides-Extra: test
Requires-Dist: pytest>=7.0; extra == "test"
Requires-Dist: pytest-asyncio>=0.21; extra == "test"
Requires-Dist: pytest-cov>=4.0; extra == "test"
Requires-Dist: hypothesis>=6.0; extra == "test"
Dynamic: license-file
